<Timestamps>
	<Entry Path="C:\Users\Admin\Desktop\Airplane Projects\A350\GitHub(public)\MSFS Project\A35X\Packages\dfd-350-k\html_ui\Pages\VCockpit\Instruments\Airliners\A350_XWB\Test\A350_PFD.png" Timestamp="13259708514" NbSourceFile="1"/>
	<Entry Path="C:\Users\Admin\Desktop\Airplane Projects\A350\GitHub(public)\MSFS Project\A35X\Packages\dfd-350-k\html_ui\Pages\VCockpit\Instruments\Airliners\A350_XWB\PFD\A350_XWB_PFD.js" Timestamp="13257977251" NbSourceFile="1"/>
	<Entry Path="C:\Users\Admin\Desktop\Airplane Projects\A350\GitHub(public)\MSFS Project\A35X\Packages\dfd-350-k\html_ui\Pages\VCockpit\Instruments\Airliners\A350_XWB\PFD\A350_XWB_PFD.html" Timestamp="13258411941" NbSourceFile="1"/>
	<Entry Path="C:\Users\Admin\Desktop\Airplane Projects\A350\GitHub(public)\MSFS Project\A35X\Packages\dfd-350-k\html_ui\Pages\VCockpit\Instruments\Airliners\A350_XWB\Test\Test.html" Timestamp="13259807523" NbSourceFile="1"/>
	<Entry Path="C:\Users\Admin\Desktop\Airplane Projects\A350\GitHub(public)\MSFS Project\A35X\Packages\dfd-350-k\html_ui\Pages\VCockpit\Instruments\generated\PFD\template.html" Timestamp="13259984513" NbSourceFile="1"/>
	<Entry Path="C:\Users\Admin\Desktop\Airplane Projects\A350\GitHub(public)\MSFS Project\A35X\Packages\dfd-350-k\html_ui\Pages\VCockpit\Instruments\generated\PFD\template.js" Timestamp="13259984513" NbSourceFile="1"/>
	<Entry Path="C:\Users\Admin\Desktop\Airplane Projects\A350\GitHub(public)\MSFS Project\A35X\Packages\dfd-350-k\html_ui\Pages\VCockpit\Instruments\Airliners\A350_XWB\Test\Test.js" Timestamp="13259712903" NbSourceFile="1"/>
	<Entry Path="C:\Users\Admin\Desktop\Airplane Projects\A350\GitHub(public)\MSFS Project\A35X\Packages\dfd-350-k\html_ui\Pages\VCockpit\Instruments\Airliners\A350_XWB\Test\Test.css" Timestamp="13257977251" NbSourceFile="1"/>
	<Entry Path="C:\Users\Admin\Desktop\Airplane Projects\A350\GitHub(public)\MSFS Project\A35X\Packages\dfd-350-k\html_ui\Pages\VCockpit\Instruments\Airliners\A350_XWB\PFD\A350_XWB_PFD.css" Timestamp="13257977251" NbSourceFile="1"/>
</Timestamps>

